Workbook

Sheet Instruccciones Generales
B1: Metodología Creciendo con su Negocio Diagnóstico Empresarial
B2: Nombre de la Empresa:
B3: Provincia:
B4: Municipio:
B5: Dirección:
B8: La presente herramienta tiene por objeto evaluar tanto las capacidades empresariales desarrolladas con las operaciones del negocio, como las capacidades emprendedoras de los miembros de la empresa.
B9: Para lograr esto se desarrollan tres cuestionarios separados: Ficha de la Empresa, Capacidades Empresariales y Capacidades emprendedoras.
B11: FICHA DEL NEGOCIO:
B12: La información de este apartado le permitirá al consultor recopilar información específica del negocio, aunque no directamente de las capacidades de los miembros, ni de la forma como realizan las operaciones actualmente. Se espera que esta información sea la base para el posterior seguimiento de la Asistencia Técnica.
B14: DIAGNÓSTICO EMPRESARIAL:
B15: Esta herramienta deberá aplicarse a la empresa/asociación que se ha incorporado al proceso de la Metodología "Creciendo con su Negocio", se busca evaluar la forma como funcionan las diferentes áreas de un negocio. Esta evaluación si bien es amplia, no tiene un nivel alto de profundidad, considerando el tiempo requerido para realizar el diagnóstico. Constituye una herramienta sencilla pero de gran utilidad para conocer de forma preliminar la situación actual de una empresa/organización y los problemas que impiden su crecimiento, sostenibilidad y desarrollo.
B16: Esta herramienta ayuda a detectar las áreas de gestión donde se requiere enfocar los esfuerzos para aplicar las medidas más efectivas para fortalecer a la empresa/asociación. Para cada una de las afirmaciones, califique a la empresa con una ponderación de 0 a 10, donde 0 significa total desacuerdo con la afirmación y 10 total acuerdo. Si alguna de las preguntas no aplica para su caso en la casilla de respuesta ingrese NA. En la hoja RESUMEN podrá visualizar un resumen del resultado obtenido por la empresa.

Sheet Ficha de la Empresa
B7: DATOS GENERALES DE LA EMPRESA
B8: La información de este apartado le permitirá al consultor recopilar información específica de la empresa, aunque no directamente de las capacidades de los miembros, ni de la forma como realizan las operaciones actualmente. Se espera que esta información sea la base para el posterior seguimiento de Asistencia Técnica que la empresa pueda requerir.
B10: INFORMACIÓN GENERAL DE LA EMPRESA/ASOCIACIÓN
B11: Nombre de la empresa: | C11: La Colmena
B12: Dirección de la empresa/asociación:
B13: Provincia:
B14: Modalidad legal de la organización:
B15: Número Total de socios (Si la organización los contenpla):
B16: Número de socias mujeres:
B17: Número de socios hombres:
B18: Empresa liderada por:
B19: Hombres:
B20: Mujeres:
B21: Empresa propiedad de:
B22: Hombres:
B23: Mujeres:
... B29: Tiempo de operación (años, meses):
B30: Opera en local propio, alquilado, en usufructo, etc | D30: Otro:
B31: Fuente de fondos para la operación | C31: Capital Propio | D31: Préstamo | E31: Otros:
B33: Actividad principal de la empresa:
B37: No. de personas contratadas:
B38: No. de mujeres contratadas:
B39: No. de hombres contratados:
B40: Del No. Total de personal, ¿cuántos tienen necesidades de cuidado y de qué tipo?
B41: Hombres: | D41: Niños/as menores de 5 años | F41: Niños/as entre 5 y 18 años | H41: Personas con discapacidad | J41: Personas adultas mayores | L41: Personas con enfermedades crónicas
B42: Mujeres:
B43: ¿Estas personas cuentan con servicios de cuidado?
B44: Sí | D44: Niños/as menores de 5 años | F44: Niños/as entre 5 y 18 años | H44: Personas con discapacidad | J44: Personas adultas mayores | L44: Personas con enfermedades crónicas
B45: No
B46: ¿El negocio tiene acceso a internet y a tecnologías digitales?
B47: Sí | D47: Celular inteligente | F47: Tablet | H47: Computadora | J47: Otro
B48: No
B49: ¿El negocio está formalizado?
B50: Sí
B51: No
B52: Página web / Redes Sociales:
B53: Nombre del contacto principal:
B54: Teléfono fijo:
B55: Teléfono Celular:
B56: Correo electrónico:
B57: Nombre de contacto 2:
B58: Teléfono fijo:
B59: Teléfono Celular:
... B93: NOMBRE DE LOS PRINCIPALES PRODUCTOS/SERVICIOS Y VENTAS
B94: Producto/Servicio | H94: Ventas mensuales $
B101: ADMINISTRACIÓN DEL NEGOCIO
B102: Nombre del Cargo | G102: Ejercido por | L102: Sexo (Hombre/Mujer) | M102: Tiempo de permanencia en el cargo
B109: Evaluación de la participación por Género en la actividad empresarial
B110: Esta sección permite determinar la distribución de funciones por género, al interior del negocio. En la medida de lo posible esta sección deberá completar por último y se deberá separar a los hombres de las mujeres para completar los datos, con el fin de evitar sesgos innecesarios de un género al otro.
B111: Actividad | J111: Mujeres | L111: Hombres
J112: Participa | K112: No Participa | L112: Participa | M112: No Participa
B113: Participación en la Junta directiva
B114: Administración de aspectos legales y fiscales
B115: Definición de la organización
B116: Registros contables y finanzas
B117: Control del plan de negocios
B118: Elaboración de los productos
B119: Aseguramiento de la calidad
B120: Búsqueda de clientes y ventas
B121: Administración de aspectos ambientales

Sheet Capacidades Empresariales
B7: DIAGNÓSTICO DE CAPACIDADES EMPRESARIALES
B9: El consultor entrevistará a los miembros de la empresa, con el fin de recopilar la información general del mismo. En los casos que sea necesario, deberá comprobar físicamente la información recibida (área de producción, equipo disponible, ubicación del mismo, actas de las sesiones de la directiva y otros que considere necesario). De requerirse, se pueden ampliar las filas para asegurarse de recabar toda la información pertinente de la empresa/asociación.
B11: Gracias a este tipo de diagnóstico se pueden detectar las áreas de gestión donde el negocio requiere enfocar los esfuerzos para aplicar las medidas más efectivas. Para cada una de las afirmaciones, califique a su empresa/asociación con una calificación de 0 a 10, donde 0 significa total desacuerdo con la afirmación y 10 total acuerdo. Si alguna de las preguntas no aplica, en la casilla de respuesta ingrese NA. En la hoja RESUMEN podrá visualizar un resumen del resultado obtenido por el negocio, tanto en forma tabular como gráfica.
B13: SITUACIÓN LEGAL Y TRIBUTARIA
D14: Evaluación | E14: Correlativo | F14: Comentarios
B15: 1 | C15: En que medida conocen los requisitos (en todos los casos) para que la empresa/asociación funcione | D15: 10 | E15: 1
B16: 2 | C16: En que medida se cumplen los requisitos para que la empresa/asociación funcione | D16: 9 | E16: =1+E15 -> 2
B17: 3 | C17: En qué medida se cumplen las obligaciones tributarias: impuesto sobre los ingresos personales, impuesto sobre utilidades, impuesto sobre las ventas/servicios, y demás | D17: 5 | E17: =1+E16 -> 3
B18: 4 | C18: En que medida se cumple con las normas laborales. | D18: 1 | E18: =1+E17 -> 4
C19: Promedio | D19: =AVERAGE(D15:D18) -> 6.25
B21: LIDERAZGO Y CLIMA ORGANIZACIONAL
D22: Evaluación | E22: Correlativo | F22: Comentarios
B23: 1 | C23: El trabajo es realmente estimulante, nos gusta. | D23: 4 | E23: =1+E18 -> 5
B24: 2 | C24: La gente parece estar orgullosa de la organización. | D24: 4 | E24: =1+E23 -> 6
B25: 3 | C25: El personal ponen gran esfuerzo en lo que hacen. | D25: 4 | E25: =1+E24 -> 7
B26: 4 | C26: El personal de jefatura se reúnen regularmente con su personal subordinado para discutir proyectos futuros. | D26: 4 | E26: =1+E25 -> 8
B27: 5 | C27: El personal de jefatura promueve el cambio y la igualdad de género. | D27: 4 | E27: =1+E26 -> 9
B28: 6 | C28: El personal de jefatura establece diálogos con el personal de la empresa/asociación. | D28: 4 | E28: =1+E27 -> 10
B29: 7 | C29: El personal de jefatura sabe delegar, convencen a la gente de cómo y porqué hacer las cosas. | D29: 4 | E29: =1+E28 -> 11
B30: 8 | C30: Los trabajos se enfocan al logro de objetivos estratégicos. | D30: 4 | E30: =1+E29 -> 12
B31: 9 | C31: El personal de jefatura promueve el empoderamiento de las mujereres que conforman su equipo | D31: 4 | E31: =1+E30 -> 13
B32: 10 | C32: El personal de jefatura apoya a que se vivan las nuevas masculinidades en un ambiente de respeto | D32: 4 | E32: =1+E31 -> 14
B33: 11 | C33: El personal de jefatura promueve la innovación en el negocio o en los productos y servicios de la empresa, incorporando las necesidades particulares de mujeres y hombres | D33: 4 | E33: =1+E32 -> 15
B34: 12 | C34: El personal de jefatura promueve que las mujeres asuman responsabilidades que usualmente son consideradas masculinas (como trabajo con maquinaria pesada o temas de finanzas por ejemplo) | D34: 4 | E34: =1+E33 -> 16
B35: 13 | C35: El personal de jefatura promueve que las hombres asuman responsabilidades que usualmente son consideradas femeninas (como secretariado, atención al cliente o recursos humanos por ejemplo) | D35: 4 | E35: =1+E34 -> 17
... B47: 25 | C47: El personal de jefatura es respetuoso del tiempo y los horarios de su gente | D47: 4 | E47: =1+E46 -> 29
C48: Promedio | D48: =AVERAGE(D23:D47) -> 4
B50: ORGANIZACIÓN
D51: Evaluación | E51: Correlativo | F51: Comentarios
B52: 1 | C52: La empresa cuenta con un organigrama claro y hay un procedimiento para elaborarlo | D52: 9 | E52: =1+E47 -> 30
B53: 2 | C53: Están claramente definidos los procedimientos para elegir los puestos directivos de la empresa/asociación | E53: =1+E52 -> 31
B54: 3 | C54: Las funciones y responsabilidades del personal están escritas y son divulgadas. | E54: =1+E53 -> 32
B55: 4 | C55: Se cuenta con procedimientos para la selección, contratación y entrenamiento del personal que están libres de discriminación y garantizan igualdad de oportunidades. | E55: =1+E54 -> 33
B56: 5 | C56: Se cuenta con un sistema de compensación que contempla la remuneración justa en dinero y otros incentivos, que están libre de discriminación y evita las brechas salariales hombre/mujer al mismo cargo. | E56: =1+E55 -> 34
B57: 6 | C57: El personal y las personas directivas tienen las competencias requeridas para el puesto que desempeñan, en función del perfil de cargo | E57: =1+E56 -> 35
B58: 7 | C58: Se cuenta con un sistema de comunicación (interno y externo) que permite dar a conocer las instrucciones de trabajo en el negocio y que es respetuoso e inclusivo. | E58: =1+E57 -> 36
B59: 8 | C59: Se cuenta con un departamento de recursos humanos que gerencia las necesidades del personal, entendiendo las necesidades particulares de mujeres y hombres. | E59: =1+E58 -> 37
B60: 9 | C60: Las prácticas de la empresa para promover la integración de la vida profesional, vida personal/familiar responden y suplen las necesidades del personal y son analizadas de manera periódica | E60: =1+E59 -> 38
B61: 10 | C61: En la empresa se respetan los horarios laborales de la gente evitando llamarles en sus horas de descanso o los fines de semana | E61: =1+E60 -> 39
B62: 11 | C62: En la empresa se tienen mecanismos de flexibilidad laboral, tanto para mujeres como para hombres | E62: =1+E61 -> 40
B63: 12 | C63: Los hombres de la empresa son alentados para que participen en labores de cuidado de niñas/os, personas adultas mayores y/o personas con discapacidad | E63: =1+E62 -> 41
B64: 13 | C64: Todos los hombres que son padres hacen uso de su licencia de paternidad y retornan a sus funciones concluido el periodo correspondiente | E64: =1+E63 -> 42
... B79: 28 | C79: Se cuida la salud y el bienestar del personal entendiendo el ciclo vital y las necesidades particulares de las mujeres y los hombres | E79: =1+E78 -> 57
C80: Promedio | D80: =AVERAGE(D52:D79) -> 9
B82: CONTABILIDAD Y FINANZAS
D83: Evaluación | E83: Correlativo | F83: Comentarios
B84: 1 | C84: Se mantiene registros contables de las operaciones del negocio. | D84: 7 | E84: =1+E79 -> 58
B85: 2 | C85: Se determinan los costos de productos/servicios del negocio | E85: =1+E84 -> 59
B86: 3 | C86: Para el presente año elaboraron un presupuesto. | E86: =1+E85 -> 60
B87: 4 | C87: Se tiene posibilidades de acceso a crédito para financiar las operaciones del negocio, aprovechando líneas de financiamiento sostenibles o de género. | E87: =1+E86 -> 61
B88: 5 | C88: Se otorga crédito a la clientela principal. | E88: =1+E87 -> 62
B89: 6 | C89: Se recibe crédito de los proveedores y se tiene un buen récord con ellos, respetando procesos justos con su cadena de valor | E89: =1+E88 -> 63
B90: 7 | C90: La gestión financiera permite asegurar que el negocio genera ganancias, con base en registros contables oportunos, precisos y transparentes | E90: =1+E89 -> 64
B91: 8 | C91: En caso de generar ganancias, esta se reparten con base en las disponibilidades del flujo de caja. | E91: =1+E90 -> 65
B92: 9 | C92: Se separa el presupuesto de la familia/accionistas y del negocio. | E92: =1+E91 -> 66
B93: 10 | C93: Se mantienen registros separados de los bienes de propiedad de la familia/accionistas y del negocio | E93: =1+E92 -> 67
C94: Promedio | D94: =AVERAGE(D84:D93) -> 7
B96: PLAN ESTRATÉGICO
D97: Evaluación | E97: Correlativo | F97: Comentarios
B98: 1 | C98: Se cuenta con un Plan Estratégico, que permite guiar las actividades del negocio y tiene un enfoque de sostenibilidad y género | D98: 5 | E98: =1+E93 -> 68
B99: 2 | C99: El Plan Estratégico sirve de base para la toma de decisiones operativas. | D99: 8 | E99: =1+E98 -> 69
B100: 3 | C100: El Plan Estratégico define indicadores y metas claras (en temas económicos, sociales, ambientales y de gobernanza) | E100: =1+E99 -> 70
B101: 4 | C101: Para el desarrollo del Plan Estratégico se tomó en cuenta las fortalezas, debilidades, oportunidades y amenazas como base para la elaboración de estrategias | E101: =1+E100 -> 71
B102: 5 | C102: Se analiza el sector de mercado en el que opera el negocio, con segmentación clara según género, edad y etnia (por lo menos) | E102: =1+E101 -> 72
B103: 6 | C103: Se cuenta con un Plan de Trabajo para el presente año, con objetivos y metas medibles y verificables, incluyendo aspectos de igualdad de género | E103: =1+E102 -> 73
B104: 7 | C104: Las actividades que se han desarrollado permiten el logro de los objetivos del Plan de Trabajo. | E104: =1+E103 -> 74
B105: 8 | C105: El presupuesto se elabora teniendo en cuenta el Plan de Trabajo. | E105: =1+E104 -> 75
C106: Promedio | D106: =AVERAGE(D98:D105) -> 6.5
B108: PRODUCCIÓN Y OPERACIONES
D109: Evaluación | E109: Correlativo | F109: Comentarios
B110: 1 | C110: La operación del negocio se mantiene activa y creciente | D110: 7 | E110: =+E105+1 -> 76
B111: 2 | C111: Los productos y servicios corresponden a las necesidades y expectativas detectadas en los/las consumidores/as según género, etnia y grupo etario. | E111: =1+E110 -> 77
B112: 3 | C112: La cantidad de máquinas y equipos con que cuenta el negocio es suficiente para atender la demanda de los productos o servicios. | E112: =1+E111 -> 78
B113: 4 | C113: Las instalaciones son suficientes y adecuadas para desarrollar las actividades del negocio y son un espacio seguro y libre de violencia para las personas que allí laboran, especialmente para las mujeres | E113: =1+E112 -> 79
B114: 5 | C114: Se conoce donde comprar las materias primas. | E114: =1+E113 -> 80
B115: 6 | C115: Las compras se hacen con base en un pronóstico de ventas y se propicia la participación de Empresas de Propiedad de Mujeres o mujeres (des ser posible). | E115: =1+E114 -> 81
B116: 8 | C116: Han desarrollado controles escritos y periódicos sobre los procesos de producción. | E116: =1+E115 -> 82
B117: 9 | C117: La capacidad instalada del negocio está siendo utilizada en su totalidad. | E117: =1+E116 -> 83
C118: Promedio | D118: =AVERAGE(D110:D117) -> 7
B120: ASEGURAMIENTO DE LA CALIDAD
D121: Evaluación | E121: Correlativo | F121: Comentarios
B122: 1 | C122: Han desarrollado por escrito la forma como se controla la calidad de los productos/servicios del negocio | D122: 3 | E122: =1+E117 -> 84
B123: 2 | C123: Cuando se está produciendo o se está ejecutando un servicio, se controla que siempre se cumpla con los procedimientos de calidad escritos. | E123: =1+E122 -> 85
B124: 3 | C124: Se analizan los resultados obtenidos en el proceso, para detectar variaciones y hacer las correcciones oportunas. | E124: =1+E123 -> 86
B125: 4 | C125: Todas las operaciones que se realizan, se registran | E125: =1+E124 -> 87
B126: 5 | C126: Existe una gestión de información de registros de operaciones, documentos u otra información importante | E126: =1+E125 -> 88
B127: 6 | C127: La empresa ha establecido que la calidad es una de las prioridades del negocio. | E127: =1+E126 -> 89
B128: 7 | C128: Los productos/ servicios del negocio se ajustan a normas técnicas. | E128: =1+E127 -> 90
C129: Promedio | D129: =AVERAGE(D122:D128) -> 3
B131: COMERCIALIZACIÓN
D132: Evaluación | E132: Correlativo | F132: Comentarios
B133: 1 | C133: Se están realizando ventas y las mismas son crecientes. | D133: 9 | E133: =1+E128 -> 91
B134: 2 | C134: Se han identificado los segmentos de mercado que atiende el negocio, según género, etnia y grupo etario. | E134: =1+E133 -> 92
B135: 3 | C135: Se conocen las características de los clientes del negocio, sus gustos y necesidades y por qué compran los productos/ servicios, según género, etnia y grupo etario. | E135: =1+E134 -> 93
B136: 4 | C136: Se conocen los hábitos de compra y de pago de los/las usuarios/as y consumidores/as. | E136: =1+E135 -> 94
B137: 5 | C137: Se conoce si la clientela está satisfecha con su producto/servicio, según género, etnia y grupo etario. | E137: =1+E136 -> 95
B138: 6 | C138: Los precios de venta se establecen con base al mercado, procurando incorporar el enfoque de género. | E138: =1+E137 -> 96
B139: 7 | C139: El personal de ventas están debidamente capacitados y son sensibles al género. | E139: =1+E138 -> 97
B140: 8 | C140: La promoción (publicidad) de los productos es adecuada, según género, etnia y grupo etario y además, es respetuosa e inclusiva. | E140: =1+E139 -> 98
B141: 9 | C141: El sistema de distribución es eficiente. | E141: =1+E140 -> 99
...

Sheet Resumen
B1: Metodología Creciendo con su Negocio Diagnóstico Empresarial
B2: Nombre de la Empres:
B3: Provincia:
B4: Departamento:
B5: Dirección:
B8: RESUMEN DE DIAGNÓSTICO EMPRESARIAL | Q8: ÁREA DE ANÁLISIS | R8: ='Ficha de la Empresa'!C11 -> La Colmena | S8: DEFICIENTE | T8: MEJORABLE | U8: ACEPTABLE
Q9: SITUACIÓN LEGAL Y FISCAL | R9: =D11 -> 6.25 | S9: 4 | T9: 7 | U9: 8
B10: # | C10: ÁREA DE ANÁLISIS | D10: Evaluación | E10: Concepto | Q10: LIDERAZGO Y CLIMA ORGANIZACIONAL | R10: =D12 -> 4 | S10: 4 | T10: 7 | U10: 8
B11: 1 | C11: SITUACIÓN LEGAL Y FISCAL | D11: ='Capacidades Empresariales'!D19 -> 6.25 | E11: =IF(D11<=4,"C: DEFICIENTE",IF(D11<=6,"B: MEJORABLE","A: ACEPTABLE")) -> A: ACEPTABLE | Q11: ORGANIZACIÓN | R11: =D13 -> 9 | S11: 4 | T11: 7 | U11: 8
B12: 2 | C12: LIDERAZGO Y CLIMA ORGANIZACIONAL | D12: ='Capacidades Empresariales'!D48 -> 4 | E12: =IF(D12<=4,"C: DEFICIENTE",IF(D12<=7,"B: MEJORABLE","A: ACEPTABLE")) -> C: DEFICIENTE | Q12: CONTABILIDAD Y FINANZAS | R12: =D14 -> 7 | S12: 4 | T12: 7 | U12: 8
B13: 3 | C13: ORGANIZACIÓN | D13: ='Capacidades Empresariales'!D80 -> 9 | E13: =IF(D13<=4,"C: DEFICIENTE",IF(D13<=7,"B: MEJORABLE","A: ACEPTABLE")) -> A: ACEPTABLE | Q13: PLAN ESTRATÉGICO | R13: =D15 -> 6.5 | S13: 4 | T13: 7 | U13: 8
B14: 4 | C14: CONTABILIDAD Y FINANZAS | D14: ='Capacidades Empresariales'!D94 -> 7 | E14: =IF(D14<=4,"C: DEFICIENTE",IF(D14<=7,"B: MEJORABLE","A: ACEPTABLE")) -> B: MEJORABLE | Q14: PRODUCCIÓN Y OPERACIONES | R14: =D16 -> 7 | S14: 4 | T14: 7 | U14: 8
B15: 5 | C15: PLAN ESTRATÉGICO | D15: ='Capacidades Empresariales'!D106 -> 6.5 | E15: =IF(D15<=4,"C: DEFICIENTE",IF(D15<=7,"B: MEJORABLE","A: ACEPTABLE")) -> B: MEJORABLE | Q15: ASEGURAMIENTO DE LA CALIDAD | R15: =D17 -> 3 | S15: 4 | T15: 7 | U15: 8
B16: 6 | C16: PRODUCCIÓN Y OPERACIONES | D16: ='Capacidades Empresariales'!D118 -> 7 | E16: =IF(D16<=4,"C: DEFICIENTE",IF(D16<=7,"B: MEJORABLE","A: ACEPTABLE")) -> B: MEJORABLE | Q16: COMERCIALIZACIÓN | R16: =D18 -> 9 | S16: 4 | T16: 7 | U16: 8
B17: 7 | C17: ASEGURAMIENTO DE LA CALIDAD | D17: ='Capacidades Empresariales'!D129 -> 3 | E17: =IF(D17<=4,"C: DEFICIENTE",IF(D17<=7,"B: MEJORABLE","A: ACEPTABLE")) -> C: DEFICIENTE
B18: 8 | C18: COMERCIALIZACIÓN | D18: ='Capacidades Empresariales'!D144 -> 9 | E18: =IF(D18<=4,"C: DEFICIENTE",IF(D18<=7,"B: MEJORABLE","A: ACEPTABLE")) -> A: ACEPTABLE
C40: ÁREA | D40: EVALUACIÓN
C41: =C11 -> SITUACIÓN LEGAL Y FISCAL | D41: =D11 -> 6.25
C42: =C12 -> LIDERAZGO Y CLIMA ORGANIZACIONAL | D42: =D12 -> 4
C43: =C13 -> ORGANIZACIÓN | D43: =D13 -> 9
C44: =C14 -> CONTABILIDAD Y FINANZAS | D44: =D14 -> 7
C45: =C15 -> PLAN ESTRATÉGICO | D45: =D15 -> 6.5
C46: =C16 -> PRODUCCIÓN Y OPERACIONES | D46: =D16 -> 7
C47: =C17 -> ASEGURAMIENTO DE LA CALIDAD | D47: =D17 -> 3
C48: =C18 -> COMERCIALIZACIÓN | D48: =D18 -> 9
C51: Este apartado deberá completarlo el consultor, como un resumen de los hallazgos realizados en la empresa que está diagnósticando.
C53: Hallazgos:
C54: 1
C55: 2
C56: 3
C57: 4
C58: 5
C60: Recomendaciones:
C61: 1
C62: 2
C63: 3
C64: 4
C65: 5
C67: BASADO EN LA PROBLEMÁTICA IDENTIFICADA, CONSTRUYA LA LÍNEA DE BASE DE LA EMPRESA/ASOCIACIÓN Y SU VALOR ESPERADO
C69: PROBLEMÁTICA | D69: LINEA DE BASE | E69: INDICADOR | F69: VALOR
F70: INICIAL | G70: ESPERADO | H70: FINAL
